Metadata-Version: 1.1
Name: coltpython
Version: 0.0.1
Summary: A framework and manager for native services.
Home-page: https://github.com/AdrianGhita/coltpython
Author: Adrian Ghiță
Author-email: adi.ghita202@gmail.com
License: MIT
Download-URL: https://github.com/AdrianGhita/coltpython.git
Keywords: coltpython service os
Platform: UNKNOWN
Classifier: Development Status :: 1 - Planning
Classifier: Environment :: No Input/Output (Daemon)
Classifier: Intended Audience :: Developers
Classifier: Topic :: Software Development :: Libraries :: Python Modules
Classifier: License :: OSI Approved :: MIT License
Classifier: Natural Language :: English
Classifier: Programming Language :: Python :: 3
Classifier: Programming Language :: Python :: 3.3
Classifier: Programming Language :: Python :: 3.4
Classifier: Programming Language :: Python :: 3.5
